mlpro_int_scikit_learn-0.4.0.dist-info/licenses/LICENSE
mlpro_int_sklearn/__init__.py
mlpro_int_sklearn/wrappers/__init__.py
mlpro_int_sklearn/wrappers/basics.py
mlpro_int_sklearn/wrappers/streams.py
mlpro_int_sklearn/wrappers/anomalydetectors/__init__.py
mlpro_int_sklearn/wrappers/anomalydetectors/basics.py
mlpro_int_scikit_learn-0.4.0.dist-info/METADATA
mlpro_int_scikit_learn-0.4.0.dist-info/WHEEL
mlpro_int_scikit_learn-0.4.0.dist-info/top_level.txt
mlpro_int_scikit_learn-0.4.0.dist-info/RECORD
