Metadata-Version: 2.4
Name: mlpro-int-scikit-learn
Version: 0.4.0
Summary: MLPro: Integration scikit-learn
Home-page: https://mlpro-int-scikit-learn.readthedocs.io
Author-email: mlpro@listen.fh-swf.de
Project-URL: Bug Tracker, https://mlpro-int-scikit-learn.readthedocs.io
Classifier: Programming Language :: Python :: 3
Classifier: License :: OSI Approved :: Apache Software License
Classifier: Operating System :: OS Independent
Requires-Python: >=3.11
License-File: LICENSE
Provides-Extra: full
Requires-Dist: mlpro[full]>=2.1.0; extra == "full"
Requires-Dist: scikit-learn>=1.7.1; extra == "full"
Dynamic: license-file
